{"is_source_file": true, "format": "Python", "description": "This file defines Flask API routes for managing products, including listing, creating, updating, deleting, and calculating total inventory balance. It uses Flask-Smorest, SQL queries, and Marshmallow schemas.", "external_files": ["../db", "../schemas"], "external_methods": ["get_connection", "abort"], "published": ["blp"], "classes": [{"name": "ProductsList", "description": "API endpoint for listing all products and creating new products."}, {"name": "ProductsBalance", "description": "API endpoint for calculating total inventory value."}, {"name": "ProductDetail", "description": "API endpoint for retrieving, updating, and deleting a specific product by ID."}], "methods": [{"name": "_row_to_product", "description": "Converts a database row to a product dictionary."}, {"name": "get", "description": "Handles GET requests for listing products, total balance, or retrieving a product by ID."}, {"name": "post", "description": "Handles POST requests to create a new product."}, {"name": "get", "description": "Handles GET request for total inventory balance."}, {"name": "get", "description": "Handles GET request for a product by ID."}, {"name": "put", "description": "Handles PUT request to update a product by ID."}, {"name": "delete", "description": "Handles DELETE request to remove a product by ID."}], "calls": ["get_connection", "conn.execute", "conn.fetchone", "abort"], "search-terms": ["products_api_backend", "products.py", "ProductSchema", "BalanceSchema", "ProductsList", "ProductsBalance", "ProductDetail", "CRUD operations", "total inventory value", "product management API"], "state": 2, "file_id": 12, "knowledge_revision": 54, "git_revision": "741d2dd0b8749fa970118dcc822acc2ac990f481", "revision_history": [{"31": ""}, {"36": "5a0f1c4968c520a6c06e7d03803dc74d14c28a0f"}, {"37": "5a0f1c4968c520a6c06e7d03803dc74d14c28a0f"}, {"42": "741d2dd0b8749fa970118dcc822acc2ac990f481"}, {"54": "741d2dd0b8749fa970118dcc822acc2ac990f481"}], "ctags": [], "filename": "products_api_backend/app/routes/products.py", "format-version": 4, "code-base-name": "https://github.com/kavia-common/product-management-api-34199-34208.git:kavia-main"}