{"is_source_file": true, "format": "Python", "description": "This file generates an OpenAPI specification from a Flask application and saves it as a JSON file in the 'interfaces' directory.", "external_files": ["app.py"], "external_methods": ["app.app_context", "api.spec.to_dict"], "published": [], "classes": [], "methods": [{"name": "none", "description": "The script contains procedural code that initializes the context, retrieves the OpenAPI spec, and writes it to a file."}], "calls": ["api.spec.to_dict", "os.makedirs", "os.path.join", "json.dump"], "search-terms": ["generate_openapi.py", "OpenAPI spec generation", "Flask app context", "api.spec"], "state": 2, "file_id": 6, "knowledge_revision": 12, "git_revision": "643b1769cf3e2a2711f43244eb1e99682477d023", "ctags": [{"_type": "tag", "name": "openapi_spec", "path": "/home/kavia/workspace/code-generation/product-management-api-34199-34208/products_api_backend/generate_openapi.py", "pattern": "/^    openapi_spec = api.spec.to_dict()$/", "language": "Python", "kind": "variable"}, {"_type": "tag", "name": "output_dir", "path": "/home/kavia/workspace/code-generation/product-management-api-34199-34208/products_api_backend/generate_openapi.py", "pattern": "/^    output_dir = \"interfaces\"$/", "language": "Python", "kind": "variable"}, {"_type": "tag", "name": "output_path", "path": "/home/kavia/workspace/code-generation/product-management-api-34199-34208/products_api_backend/generate_openapi.py", "pattern": "/^    output_path = os.path.join(output_dir, \"openapi.json\")$/", "language": "Python", "kind": "variable"}], "hash": "65ec7d3cc6c826bade677c81704d7819", "format-version": 4, "code-base-name": "products_api_backend", "filename": "products_api_backend/generate_openapi.py", "fields": [{"name": "openapi_spec = api.spec.to_dict()", "scope": "", "scopeKind": "", "description": "unavailable"}, {"name": "output_dir = \"interfaces\"", "scope": "", "scopeKind": "", "description": "unavailable"}, {"name": "output_path = os.path.join(output_dir, \"openapi.json\")", "scope": "", "scopeKind": "", "description": "unavailable"}], "revision_history": [{"12": "643b1769cf3e2a2711f43244eb1e99682477d023"}]}